README.rst
setup.cfg
setup.py
libtf/__init__.py
libtf.egg-info/PKG-INFO
libtf.egg-info/SOURCES.txt
libtf.egg-info/dependency_links.txt
libtf.egg-info/requires.txt
libtf.egg-info/top_level.txt
libtf/logparsers/__init__.py
libtf/logparsers/tf_auth_log.py
libtf/logparsers/tf_exceptions.py
libtf/logparsers/tf_generic_log.py
libtf/logparsers/tf_http_log.py
libtf/logparsers/tf_log_base.py