Metadata-Version: 1.1
Name: libtf
Version: 0.1.2
Summary: Threshing Floor python module for analyzing and reducing noise from log files.
Home-page: https://github.com/ThreshingFloor/libtf
Author: Threshing Floor Security, LLC
Author-email: info@threshingfloor.io
License: MIT
Platform: UNKNOWN
Classifier: Development Status :: 3 - Alpha
